HISTORY.md
LICENSE
MANIFEST.in
README.md
requirements.txt
requirements_dev.txt
setup.cfg
setup.py
versioneer.py
run_web_pycode/__init__.py
run_web_pycode/__main__.py
run_web_pycode/_version.py
run_web_pycode/core.py
run_web_pycode.egg-info/PKG-INFO
run_web_pycode.egg-info/SOURCES.txt
run_web_pycode.egg-info/dependency_links.txt
run_web_pycode.egg-info/entry_points.txt
run_web_pycode.egg-info/requires.txt
run_web_pycode.egg-info/top_level.txt
tests/__init__.py
tests/a_script.py
tests/test_cli.py
tests/test_run_web_pycode.py