Metadata-Version: 2.1
Name: run-web-pycode
Version: 0.0.1
Summary: A package to execute remote python scripts
Home-page: https://github.com/AngusWG/run-web-pycode
Author: AngusWG
Author-email: 740713651@qq.com
License: MIT license
Keywords: run_web_pycode
Platform: UNKNOWN
Classifier: Development Status :: 2 - Pre-Alpha
Classifier: Intended Audience :: Developers
Classifier: License :: OSI Approved :: MIT License
Classifier: Natural Language :: English
Classifier: Programming Language :: Python :: 3.6
Classifier: Programming Language :: Python :: 3.7
Classifier: Programming Language :: Python :: 3.8
Classifier: Programming Language :: Python :: 3.9
Requires-Python: >=3.6
Provides-Extra: dev_require
